{
    "license_title": "Creative Commons Attribution 4.0",
    "maintainer": "Open Data Team",
    "relationships_as_object": [],
    "private": false,
    "maintainer_email": "opendata@edostate.gov.ng",
    "revision_timestamp": "2014-11-06T16:31:19.605466",
    "id": "61b87550-d3b9-4dde-aa27-6ae1aaf3da36",
    "metadata_created": "2014-11-06T16:31:19.605466",
    "owner_org": null,
    "metadata_modified": "2014-12-18T16:45:57.536519",
    "author": "National Population Commission",
    "author_email": "opendata@edostate.gov.ng",
    "state": "active",
    "version": null,
    "license_id": "CC-BY-4.0",
    "type": "dataset",
    "resources": [
        {
            "resource_group_id": "70bf8a69-ad4b-4a34-a8d5-19f44fb88770",
            "cache_last_updated": null,
            "revision_timestamp": "2014-12-18T16:45:57.536519",
            "webstore_last_updated": "2014-07-08T13:26:07.198149",
            "id": "aed36382-f0c7-40c2-9cad-42de95b13852",
            "size": "875",
            "state": "active",
            "hash": "{\"content\": \"08c8435d78e2f9c174a5151150efca755ac18212\", \"header\": \"3c8346afb865c4d1aa7c7645acc747d12eecfbe1\"}",
            "description": "Distribution of Population (Age 6 and Above) by Sex, Age Group and Literary Status in Edo State",
            "format": "CSV",
            "tracking_summary": {
                "total": 0,
                "recent": 0
            },
            "mimetype_inner": null,
            "mimetype": "text/csv",
            "cache_url": null,
            "name": "Distribution of Population (Age 6 and above) by Sex, Age Groups and Literacy Status.csv",
            "created": "2013-08-28T10:59:44.204682",
            "url": "http://data.edostate.gov.ng/storage/f/2013-08-28T10%3A54%3A50.586Z/distribution-of-population-age-6-and-above-by-sex-age-groups-and-literacy-status.csv",
            "webstore_url": "active",
            "last_modified": "2014-07-08T13:25:34.304547",
            "position": 0,
            "revision_id": "81f80d5f-86f3-4e61-bb1f-cf3737876f9c",
            "resource_type": "file.upload",
            "resource_reachable": true
        }
    ],
    "num_resources": 1,
    "tags": [
        {
            "vocabulary_id": null,
            "display_name": "NPC",
            "name": "NPC",
            "revision_timestamp": "2014-11-06T16:31:19.605466",
            "state": "active",
            "id": "73de67c7-a256-4e36-bb82-aa657519fa68"
        },
        {
            "vocabulary_id": null,
            "display_name": "Population Census",
            "name": "Population Census",
            "revision_timestamp": "2014-11-06T16:31:19.605466",
            "state": "active",
            "id": "a992c864-bcdf-4367-b2ad-35e23b6f81b4"
        },
        {
            "vocabulary_id": null,
            "display_name": "africa",
            "name": "africa",
            "revision_timestamp": "2014-11-06T16:31:19.605466",
            "state": "active",
            "id": "d64e7b09-4344-478e-b93f-8c51e5c3110b"
        },
        {
            "vocabulary_id": null,
            "display_name": "edo state",
            "name": "edo state",
            "revision_timestamp": "2014-11-06T16:31:19.605466",
            "state": "active",
            "id": "b7ac55fa-8449-416f-be17-e59c4c154e51"
        },
        {
            "vocabulary_id": null,
            "display_name": "nigeria",
            "name": "nigeria",
            "revision_timestamp": "2014-11-06T16:31:19.605466",
            "state": "active",
            "id": "d5e39c15-faf7-4e35-96a0-cb88ec7becb1"
        },
        {
            "vocabulary_id": null,
            "display_name": "open data",
            "name": "open data",
            "revision_timestamp": "2014-11-06T16:31:19.605466",
            "state": "active",
            "id": "5977073f-ae9b-420d-b468-636bfcf752de"
        },
        {
            "vocabulary_id": null,
            "display_name": "west africa",
            "name": "west africa",
            "revision_timestamp": "2014-11-06T16:31:19.605466",
            "state": "active",
            "id": "82a06d2c-708d-44e5-b6c4-0aef079cbf6c"
        },
        {
            "vocabulary_id": null,
            "display_name": "western africa",
            "name": "western africa",
            "revision_timestamp": "2014-11-06T16:31:19.605466",
            "state": "active",
            "id": "0297e4dc-f3f3-4b3a-bf41-50dd715a453a"
        }
    ],
    "tracking_summary": {
        "total": 2,
        "recent": 2
    },
    "groups": [
        {
            "title": "Nigeria",
            "description": "Datasets from the Republic of Nigeria",
            "name": "nigeria",
            "id": "6e482307-7e70-4db4-a3f2-91db4e2b90bc"
        }
    ],
    "relationships_as_subject": [],
    "num_tags": 8,
    "name": "distribution-of-population-age-6-and-above-by-sex-age-groups-and-literacy-status1",
    "isopen": true,
    "url": null,
    "notes": "Distribution of Population (Age 6 and Above) by Sex, Age Group and Literary Status in Edo State",
    "title": "Distribution of Population (Age 6 and above) by Sex, Age Groups and Literacy Status",
    "extras": [],
    "license_url": "https://creativecommons.org/licenses/by/4.0/",
    "organization": null,
    "revision_id": "8a678ec6-87f7-44f9-b9b3-96578b33d1be",
    "license_information": {
        "domain_content": true,
        "domain_data": true,
        "domain_software": false,
        "family": "",
        "od_conformance": "approved",
        "osd_conformance": "not reviewed",
        "maintainer": "Creative Commons",
        "status": "active"
    }
}