{
    "license_title": "License Not Specified",
    "maintainer": null,
    "relationships_as_object": [],
    "private": false,
    "maintainer_email": null,
    "revision_timestamp": "2014-11-12T22:53:14.336089",
    "id": "02108608-6b1d-4456-9719-1937343c1fb6",
    "metadata_created": "2014-11-12T22:53:14.336089",
    "owner_org": "d053dbc0-7a56-4798-b138-1e377618d497",
    "metadata_modified": "2014-11-12T22:53:21.158799",
    "author": null,
    "author_email": null,
    "state": "active",
    "version": null,
    "license_id": "notspecified",
    "type": "dataset",
    "resources": [
        {
            "resource_group_id": "5be32c5f-c1f1-4443-9267-6bf7d379d40b",
            "resource_description": "The data codebook for IBLI Borena Household Survey. This is September 20th, 2014 version, which revised “Section 2.3. Weighting Factors” and “Section 6.1. Suggested Citation for Acknowledgement” from the initial public release version on August 15th, 2014. ",
            "cache_last_updated": null,
            "revision_timestamp": "2014-11-12T22:53:19.279922",
            "webstore_last_updated": null,
            "id": "09d82a75-d742-4df9-81b7-27a046aa1417",
            "size": "9370",
            "state": "active",
            "hash": "da4e3bd1a181ae5ee4c8980285110b16be8ec517",
            "description": "{\"resource_description\":\"The data codebook for IBLI Borena Household Survey. This is September 20th, 2014 version, which revised “Section 2.3. Weighting Factors” and “Section 6.1. Suggested Citation for Acknowledgement” from the initial public release version on August 15th, 2014. \",\"resource_access\":\"Public\"}",
            "format": "PDF",
            "tracking_summary": {
                "total": 6,
                "recent": 1
            },
            "mimetype_inner": null,
            "mimetype": "text/html",
            "cache_url": null,
            "name": "IBLI Borena Household Survey Codebook",
            "created": "2014-08-26T15:03:41.553909",
            "url": "http://data.ilri.org/portal/",
            "webstore_url": null,
            "last_modified": "2014-11-12T22:53:19.117315",
            "position": 0,
            "revision_id": "60523ff3-541a-4f21-9da9-c8ed70e09f0d",
            "ILRIResourceAccess": "Public",
            "resource_type": null,
            "resource_reachable": true
        },
        {
            "resource_group_id": "5be32c5f-c1f1-4443-9267-6bf7d379d40b",
            "resource_description": "Zip file of IBLI Borena Household Survey R2 Stata 13 data (.dta) files. This is August 26th, 2014 version, which corrects weight variable in the initial public release version on August 15th, 2014. ",
            "cache_last_updated": null,
            "revision_timestamp": "2014-11-12T22:53:21.158799",
            "webstore_last_updated": null,
            "id": "2c865b6f-b760-4375-84bb-4f39fc488fe3",
            "size": "9370",
            "state": "active",
            "hash": "da4e3bd1a181ae5ee4c8980285110b16be8ec517",
            "description": "{\"resource_description\":\"Zip file of IBLI Borena Household Survey R2 Stata 13 data (.dta) files. This is August 26th, 2014 version, which corrects weight variable in the initial public release version on August 15th, 2014. \",\"resource_access\":\"Public\"}",
            "format": "ZIP",
            "tracking_summary": {
                "total": 6,
                "recent": 1
            },
            "mimetype_inner": null,
            "mimetype": "text/html",
            "cache_url": null,
            "name": "IBLI Borena Household Survey R2 Stata data",
            "created": "2014-08-26T12:33:20.310996",
            "url": "http://data.ilri.org/portal/",
            "webstore_url": null,
            "last_modified": "2014-11-12T22:53:20.974028",
            "position": 1,
            "revision_id": "71fe9d26-8fc1-4949-9635-9b3ab9331b62",
            "ILRIResourceAccess": "Public",
            "resource_type": null,
            "resource_reachable": true
        },
        {
            "resource_group_id": "5be32c5f-c1f1-4443-9267-6bf7d379d40b",
            "resource_description": "Report on the content of IBLI Borena Household Survey R2 Questionnaire generated with surveybe (Computer-Assisted Personal Interviewing (CAPI) software).",
            "cache_last_updated": null,
            "revision_timestamp": "2014-11-12T22:53:17.231251",
            "webstore_last_updated": null,
            "id": "baa6903f-3932-4da7-aeaa-5f9b2ce15243",
            "size": "9370",
            "state": "active",
            "hash": "da4e3bd1a181ae5ee4c8980285110b16be8ec517",
            "description": "{\"resource_description\":\"Report on the content of IBLI Borena Household Survey R2 Questionnaire generated with surveybe (Computer-Assisted Personal Interviewing (CAPI) software).\",\"resource_access\":\"Public\"}",
            "format": "PDF",
            "tracking_summary": {
                "total": 6,
                "recent": 1
            },
            "mimetype_inner": null,
            "mimetype": "text/html",
            "cache_url": null,
            "name": "IBLI Borena Household Survey R2 Questionnaire Content Report",
            "created": "2014-08-25T18:35:27.930297",
            "url": "http://data.ilri.org/portal/",
            "webstore_url": null,
            "last_modified": "2014-11-12T22:53:17.071139",
            "position": 2,
            "revision_id": "4e609db5-1867-4f3e-8e0d-5395d630ff61",
            "ILRIResourceAccess": "Public",
            "resource_type": null,
            "resource_reachable": true
        }
    ],
    "num_resources": 3,
    "tags": [
        {
            "vocabulary_id": null,
            "display_name": "Impact assessment",
            "name": "Impact assessment",
            "revision_timestamp": "2014-11-12T22:53:14.336089",
            "state": "active",
            "id": "41566099-b31f-484e-bea0-429af111fe9a"
        },
        {
            "vocabulary_id": null,
            "display_name": "drought",
            "name": "drought",
            "revision_timestamp": "2014-11-12T22:53:14.336089",
            "state": "active",
            "id": "16d4ef97-54e1-4fef-a255-bcac56d5f6d2"
        },
        {
            "vocabulary_id": null,
            "display_name": "dryland",
            "name": "dryland",
            "revision_timestamp": "2014-11-12T22:53:14.336089",
            "state": "active",
            "id": "50a7c3ed-32bd-4695-a101-e9a5c6f9ec8e"
        },
        {
            "vocabulary_id": null,
            "display_name": "food security",
            "name": "food security",
            "revision_timestamp": "2014-11-12T22:53:14.336089",
            "state": "active",
            "id": "bc86b5cf-267e-460b-a531-3a7e495a3eb0"
        },
        {
            "vocabulary_id": null,
            "display_name": "insurance",
            "name": "insurance",
            "revision_timestamp": "2014-11-12T22:53:14.336089",
            "state": "active",
            "id": "62049c5c-a6f1-4d5e-a6f9-3c49c09b1bce"
        },
        {
            "vocabulary_id": null,
            "display_name": "livestock",
            "name": "livestock",
            "revision_timestamp": "2014-11-12T22:53:14.336089",
            "state": "active",
            "id": "0ad5c5be-d2e6-4413-b40f-b94ec97ab91a"
        },
        {
            "vocabulary_id": null,
            "display_name": "pastoralism",
            "name": "pastoralism",
            "revision_timestamp": "2014-11-12T22:53:14.336089",
            "state": "active",
            "id": "dc8b4ecc-1916-45d0-a09a-8de6d76a500c"
        },
        {
            "vocabulary_id": null,
            "display_name": "poverty",
            "name": "poverty",
            "revision_timestamp": "2014-11-12T22:53:14.336089",
            "state": "active",
            "id": "490c0df0-0458-4e36-8ad1-2fa9d0684d97"
        }
    ],
    "tracking_summary": {
        "total": 10,
        "recent": 1
    },
    "groups": [],
    "relationships_as_subject": [],
    "num_tags": 8,
    "name": "ibli-borena-r2",
    "isopen": false,
    "url": "http://data.ilri.org/portal/",
    "notes": "The second (follow-up) round of socio-economic household survey to evaluate the impact of Index Based Livestock Insurance (IBLI) in Borena Zone, Southern Ethiopia. \r\n\r\nInternational Livestock Research Institute (ILRI) and Cornell University in collaboration with implementing partners Oromia Insurance Company (OIC) and Oromia Credits and Saving Share Company (OCSSCO) piloted in August 2012 a market-mediated index-based insurance product, designed to protect pastoralists from drought-related livestock mortality, in the Borena Zone. Basic product design, household survey, and evaluation strategy mimic and complement that of a previously designed IBLI product in the Marsabit district of Northern Kenya, first rolled out two years earlier (2010).\r\n\r\nTo better understand and monitor the success of IBLI, there is the need for continuous impact evaluation and assessment, tracking the changes in well-being of individual households that can be attributed to the program and product. To that end, the IBLI team carried out a pre-intervention baseline survey (February-March 2012) and complemented it with annual follow-up rounds in 2013 and 2014 (with a future-scheduled round in 2015). \r\nThe details of the survey and the data are described in the data codebook. For more general information on the research and development process of the IBLI products and pilots, visit www.ilri.org/ibli and http://livestockinsurance.wordpress.com/ibli-southern-ethiopia.",
    "title": "Index Based Livestock Insurance (IBLI) Borena Household Survey Round 2",
    "extras": [
        {
            "value": "{\"southWestLat\":3.3809669227276355,\"southWestLong\":36.802825927734375,\"northEastLat\":5.735388857288777,\"northEastLong\":40.76889038085937}",
            "key": "ILRI_actyboundbox",
            "__extras": {
                "revision_id": "beea23b0-e64b-405f-9607-5857bb6baa80",
                "package_id": "02108608-6b1d-4456-9719-1937343c1fb6"
            }
        },
        {
            "value": "4.558177890008206,38.785858154296875",
            "key": "ILRI_actyboundboxcenter",
            "__extras": {
                "revision_id": "beea23b0-e64b-405f-9607-5857bb6baa80",
                "package_id": "02108608-6b1d-4456-9719-1937343c1fb6"
            }
        },
        {
            "value": "Index Based Livestock Insurance (IBLI) Borena Household Survey Round 2",
            "key": "ILRI_actycitation",
            "__extras": {
                "revision_id": "beea23b0-e64b-405f-9607-5857bb6baa80",
                "package_id": "02108608-6b1d-4456-9719-1937343c1fb6"
            }
        },
        {
            "value": "This publication was made possible by access to data collected by the Index Based Livestock Insurance (IBLI) Project, a collaborative effort of the International Livestock Research Institute (ILRI), Cornell University, Syracuse University, the BASIS Research Program at the University of California at Davis, and the University of Sydney.  Data collection was made possible, in part, by support provided by the US Agency for International Development (USAID) Agreement No. LAG---A---00---96---90016---00 through Broadening Access and Strengthening Input Market Systems Collaborative Research Support Program (BASIS AMA CRSP), the Department of Foreign Affairs and Trade through the Australia Development Research Awards Scheme under an award titled “The human and environmental impacts of migratory pastoralism in arid and semi-arid East Africa”, and CGIAR Research Programs on Climate Change, Agriculture and Food Security (CCAFS) and Dryland Systems. All views and interpretations expressed in this publication are those of the authors and not necessarily those of the supporting or cooperating institutions. ",
            "key": "ILRI_actycitationacknowledge",
            "__extras": {
                "package_id": "02108608-6b1d-4456-9719-1937343c1fb6",
                "revision_id": "beea23b0-e64b-405f-9607-5857bb6baa80"
            }
        },
        {
            "value": "m.ikegami@cgiar.org",
            "key": "ILRI_actycontactemail",
            "__extras": {
                "package_id": "02108608-6b1d-4456-9719-1937343c1fb6",
                "revision_id": "beea23b0-e64b-405f-9607-5857bb6baa80"
            }
        },
        {
            "value": "Munenobu Ikegami",
            "key": "ILRI_actycontactperson",
            "__extras": {
                "package_id": "02108608-6b1d-4456-9719-1937343c1fb6",
                "revision_id": "beea23b0-e64b-405f-9607-5857bb6baa80"
            }
        },
        {
            "value": "International Livestock Research Institute",
            "key": "ILRI_actydataowner",
            "__extras": {
                "revision_id": "beea23b0-e64b-405f-9607-5857bb6baa80",
                "package_id": "02108608-6b1d-4456-9719-1937343c1fb6"
            }
        },
        {
            "value": "15/08/2014",
            "key": "ILRI_actydatavailable",
            "__extras": {
                "package_id": "02108608-6b1d-4456-9719-1937343c1fb6",
                "revision_id": "beea23b0-e64b-405f-9607-5857bb6baa80"
            }
        },
        {
            "value": "12/03/2013",
            "key": "ILRI_actydatecollected",
            "__extras": {
                "revision_id": "beea23b0-e64b-405f-9607-5857bb6baa80",
                "package_id": "02108608-6b1d-4456-9719-1937343c1fb6"
            }
        },
        {
            "value": "{\"southWestLat\":2.3504147112508305,\"southWestLong\":34.92553710937499,\"northEastLat\":6.5118147063479,\"northEastLong\":41.68212890625}",
            "key": "ILRI_actymapextent",
            "__extras": {
                "package_id": "02108608-6b1d-4456-9719-1937343c1fb6",
                "revision_id": "beea23b0-e64b-405f-9607-5857bb6baa80"
            }
        },
        {
            "value": "7",
            "key": "ILRI_actymapzoom",
            "__extras": {
                "package_id": "02108608-6b1d-4456-9719-1937343c1fb6",
                "revision_id": "beea23b0-e64b-405f-9607-5857bb6baa80"
            }
        },
        {
            "value": "Oromia Region,Borena Zone",
            "key": "ILRI_actynatlevel",
            "__extras": {
                "revision_id": "beea23b0-e64b-405f-9607-5857bb6baa80",
                "package_id": "02108608-6b1d-4456-9719-1937343c1fb6"
            }
        },
        {
            "value": "Chris Barrett, Russell Toth, Megan Sheahan, Samuel Mburu, Kazushi Takahashi, Liz Bageant, Nathaniel Jensen, Kibrom Hirfrfot, Amy Kahn",
            "key": "ILRI_actypartners",
            "__extras": {
                "revision_id": "beea23b0-e64b-405f-9607-5857bb6baa80",
                "package_id": "02108608-6b1d-4456-9719-1937343c1fb6"
            }
        },
        {
            "value": "Andrew Mude",
            "key": "ILRI_actypi",
            "__extras": {
                "revision_id": "beea23b0-e64b-405f-9607-5857bb6baa80",
                "package_id": "02108608-6b1d-4456-9719-1937343c1fb6"
            }
        },
        {
            "value": "",
            "key": "ILRI_actysharingagreement",
            "__extras": {
                "revision_id": "beea23b0-e64b-405f-9607-5857bb6baa80",
                "package_id": "02108608-6b1d-4456-9719-1937343c1fb6"
            }
        },
        {
            "value": "Munenobu Ikegami, Birhanu Taddesse, Wako Gobu, Anne Gesare, Philemon Chelanga, Oscar Naibei, Eddy Chebelyon, Mohamed Shibia, ",
            "key": "ILRI_actystaff",
            "__extras": {
                "package_id": "02108608-6b1d-4456-9719-1937343c1fb6",
                "revision_id": "beea23b0-e64b-405f-9607-5857bb6baa80"
            }
        },
        {
            "value": "All publications based on the data will give due acknowledgement to the project for its role in generating the data and to the US Agency for International Development (USAID), Australian Department of Foreign Affairs and Trade, and CGIAR Research Programs for financing their collection. An attribution statement similar to that provided in the \"Citation for acknowledgment\" section below should be included.  \r\nFor the purpose of maintaining a comprehensive archive of studies based on these data, authors of publicly released studies using these data must provide a copy of the studies to Munenobu Ikegami (email: m.ikegami@cgiar.org). ",
            "key": "ILRI_actyusageconditions",
            "__extras": {
                "package_id": "02108608-6b1d-4456-9719-1937343c1fb6",
                "revision_id": "beea23b0-e64b-405f-9607-5857bb6baa80"
            }
        },
        {
            "value": "Since 2008, ILRI and its partners in the public, private, and non-profit sectors have pursued a comprehensive research agenda aimed at designing, developing, and implementing market-mediated index-based insurance to protect livestock keepers from drought related asset losses, particularly those in the drought prone Arid and Semi-Arid Lands (ASALs). For pastoralists whose livelihoods rely solely or partly on livestock, the resulting high livestock mortality rate has devastating effects on asset levels, rendering them among the most vulnerable populations in Kenya and Ethiopia.\r\nIndex-based insurance represents an exciting innovation that could allow vulnerable rural smallholder farmers and livestock keepers to benefit from insurance and thus reduce climate-related risk. Because index insurance is based on the realization of an outcome that cannot be influenced by insurers or policy holders (such as the amount and distribution of rainfall over a season), it has a relatively simple and transparent structure. This makes such products easier to administer and consequently more cost-effective to develop and trade. Indeed the success of several pilot programs in India and various countries in Africa and Latin America has proven the feasibility and affordability of such products.",
            "key": "ILRI_prjabstract",
            "__extras": {
                "revision_id": "beea23b0-e64b-405f-9607-5857bb6baa80",
                "package_id": "02108608-6b1d-4456-9719-1937343c1fb6"
            }
        },
        {
            "value": "KENYA+ETHIOPIA",
            "key": "ILRI_prjcountries",
            "__extras": {
                "revision_id": "beea23b0-e64b-405f-9607-5857bb6baa80",
                "package_id": "02108608-6b1d-4456-9719-1937343c1fb6"
            }
        },
        {
            "value": "USAID, UKAID, AusAID, World Bank, ILO, BASIS, I4, CRP7, CRP1.1",
            "key": "ILRI_prjdonor",
            "__extras": {
                "package_id": "02108608-6b1d-4456-9719-1937343c1fb6",
                "revision_id": "beea23b0-e64b-405f-9607-5857bb6baa80"
            }
        },
        {
            "value": "31/03/2016",
            "key": "ILRI_prjedate",
            "__extras": {
                "revision_id": "beea23b0-e64b-405f-9607-5857bb6baa80",
                "package_id": "02108608-6b1d-4456-9719-1937343c1fb6"
            }
        },
        {
            "value": "UOC001 IS04 ADD, CG703 IS03 ADD",
            "key": "ILRI_prjgrant",
            "__extras": {
                "package_id": "02108608-6b1d-4456-9719-1937343c1fb6",
                "revision_id": "beea23b0-e64b-405f-9607-5857bb6baa80"
            }
        },
        {
            "value": "Cornell University, the BASIS Research Program at the University of California at Davis, the University of Sydney, Syracuse University, Oromiya Insurance Company, Oromia Credits and Saving Share Company (OCSSCO), APA Insurance Company, Takaful Insurance",
            "key": "ILRI_prjpartners",
            "__extras": {
                "revision_id": "beea23b0-e64b-405f-9607-5857bb6baa80",
                "package_id": "02108608-6b1d-4456-9719-1937343c1fb6"
            }
        },
        {
            "value": "Andrew Mude",
            "key": "ILRI_prjpi",
            "__extras": {
                "package_id": "02108608-6b1d-4456-9719-1937343c1fb6",
                "revision_id": "beea23b0-e64b-405f-9607-5857bb6baa80"
            }
        },
        {
            "value": "EAST AFRICA",
            "key": "ILRI_prjregions",
            "__extras": {
                "revision_id": "beea23b0-e64b-405f-9607-5857bb6baa80",
                "package_id": "02108608-6b1d-4456-9719-1937343c1fb6"
            }
        },
        {
            "value": "01/01/2008",
            "key": "ILRI_prjsdate",
            "__extras": {
                "package_id": "02108608-6b1d-4456-9719-1937343c1fb6",
                "revision_id": "beea23b0-e64b-405f-9607-5857bb6baa80"
            }
        },
        {
            "value": "CATTLE,CAMELS,GOAT,SHEEP",
            "key": "ILRI_prjspecies",
            "__extras": {
                "revision_id": "beea23b0-e64b-405f-9607-5857bb6baa80",
                "package_id": "02108608-6b1d-4456-9719-1937343c1fb6"
            }
        },
        {
            "value": "Munenobu Ikegami, Bryn Davies, Apurba Shee, Brenda Wandera, Birhanu Taddesse, Wako Gobu, Anne Gesare, Philemon Chelanga, Oscar Naibei, Eddy Chebelyon, Mohamed Shibia, Diba Galgallo, Rupsha Banerjee, Duncan Khalai",
            "key": "ILRI_prjstaff",
            "__extras": {
                "package_id": "02108608-6b1d-4456-9719-1937343c1fb6",
                "revision_id": "beea23b0-e64b-405f-9607-5857bb6baa80"
            }
        },
        {
            "value": "Index Based Livestock Insurance (IBLI) Project",
            "key": "ILRI_prjtitle",
            "__extras": {
                "revision_id": "beea23b0-e64b-405f-9607-5857bb6baa80",
                "package_id": "02108608-6b1d-4456-9719-1937343c1fb6"
            }
        },
        {
            "value": "www.ilri.org/ibli",
            "key": "ILRI_prjwebsite",
            "__extras": {
                "package_id": "02108608-6b1d-4456-9719-1937343c1fb6",
                "revision_id": "beea23b0-e64b-405f-9607-5857bb6baa80"
            }
        }
    ],
    "organization": {
        "description": "The International Livestock Research Institute (ILRI) works to improve food security and reduce poverty in developing countries through research for better and more sustainable use of livestock. ILRI is a member of the CGIAR Consortium which works for a food-secure future.",
        "title": "ILRI",
        "created": "2014-08-19T09:51:48.312508",
        "approval_status": "approved",
        "revision_timestamp": "2014-08-19T09:51:48.269962",
        "is_organization": true,
        "state": "active",
        "image_url": "http://www.fangrvn.com/upload/ilri_logo_color_1377842099.jpg",
        "revision_id": "628af016-a0e5-4abb-8fa0-78160498318f",
        "type": "organization",
        "id": "d053dbc0-7a56-4798-b138-1e377618d497",
        "name": "ilri"
    },
    "revision_id": "beea23b0-e64b-405f-9607-5857bb6baa80"
}