{
    "license_title": "Other (Public Domain)",
    "maintainer": "Samuel Kipruto",
    "relationships_as_object": [],
    "private": false,
    "maintainer_email": null,
    "revision_timestamp": "2012-09-11T13:54:37.848551",
    "id": "aa963d43-f215-4b82-b1e4-9f7832f52467",
    "metadata_created": "2012-09-11T13:54:37.848551",
    "owner_org": null,
    "metadata_modified": "2013-10-10T12:03:48.201648",
    "author": "Samuel Kipruto",
    "author_email": null,
    "state": "active",
    "version": null,
    "license_id": "other-pd",
    "type": "dataset",
    "resources": [
        {
            "resource_group_id": "970fa731-5664-48e7-bedf-ebf407762f59",
            "cache_last_updated": null,
            "revision_timestamp": "2013-10-10T12:03:48.201648",
            "webstore_last_updated": "2013-10-10T12:03:48.021791",
            "id": "93ec4587-db82-4ef9-8418-22b631786456",
            "size": "3293",
            "state": "active",
            "hash": "d73babab2c777ac37507b253142964f5ff1d569a",
            "description": "",
            "format": "CSV",
            "tracking_summary": {
                "total": 0,
                "recent": 0
            },
            "mimetype_inner": null,
            "mimetype": "text/csv",
            "cache_url": null,
            "name": "Expenditure On The Gross Domestic Product Percentage Shares 2001-2009.csv",
            "created": "2012-09-11T13:54:37.880242",
            "url": "http://africaopendata.org/storage/f/2012-09-11T155722/seua-azc7.csv",
            "webstore_url": "active",
            "last_modified": "2013-03-13T23:15:18.239630",
            "position": 0,
            "revision_id": "911f601d-8c02-4964-8b0d-084c31d2a3b6",
            "resource_type": "file.upload",
            "resource_reachable": true
        }
    ],
    "num_resources": 1,
    "tags": [
        {
            "vocabulary_id": null,
            "display_name": "kenya",
            "name": "kenya",
            "revision_timestamp": "2012-09-11T13:54:37.848551",
            "state": "active",
            "id": "3f582e66-8113-4a99-8d18-5647ab436eda"
        },
        {
            "vocabulary_id": null,
            "display_name": "kodi",
            "name": "kodi",
            "revision_timestamp": "2012-09-11T13:54:37.848551",
            "state": "active",
            "id": "8c95d71f-854f-4c7a-8eda-6dfc008df9c1"
        }
    ],
    "tracking_summary": {
        "total": 38,
        "recent": 2
    },
    "groups": [
        {
            "title": "Kenya",
            "description": "Datasets from Kenya",
            "name": "kenya",
            "id": "cdaf12d8-27b2-4cd4-9504-402a45012576"
        }
    ],
    "relationships_as_subject": [],
    "num_tags": 2,
    "name": "kodi-seua-azc7",
    "isopen": true,
    "url": "http://www.knbs.or.ke",
    "notes": "Kenya National Bureau of Statistics     Expenditure On The Gross Domestic Product Percentage Shares 2001-2009   Staistical Abstract",
    "title": "Expenditure On The Gross Domestic Product Percentage Shares 2001-2009",
    "extras": [
        {
            "value": "Kenya national Bureau of Statistics",
            "key": "attribution",
            "__extras": {
                "revision_id": "59a33a10-0dad-4597-b4c2-297d18408daf",
                "package_id": "aa963d43-f215-4b82-b1e4-9f7832f52467"
            }
        },
        {
            "value": "    National Accounts And Inflation",
            "key": "category",
            "__extras": {
                "revision_id": "59a33a10-0dad-4597-b4c2-297d18408daf",
                "package_id": "aa963d43-f215-4b82-b1e4-9f7832f52467"
            }
        },
        {
            "value": "This dataset has been automatically imported from the Kenya Open Data Portal",
            "key": "comment",
            "__extras": {
                "revision_id": "59a33a10-0dad-4597-b4c2-297d18408daf",
                "package_id": "aa963d43-f215-4b82-b1e4-9f7832f52467"
            }
        }
    ],
    "organization": null,
    "revision_id": "59a33a10-0dad-4597-b4c2-297d18408daf"
}