{
    "license_title": "Other (Public Domain)",
    "maintainer": "Kenya Visualization Bot",
    "relationships_as_object": [],
    "private": false,
    "maintainer_email": null,
    "revision_timestamp": "2012-09-10T11:59:44.672681",
    "id": "f1efbe98-ae6e-457e-945c-bb3ef1e61028",
    "metadata_created": "2012-09-10T11:59:44.672681",
    "owner_org": null,
    "metadata_modified": "2013-10-10T12:16:47.471028",
    "author": "Chris Metcalf",
    "author_email": null,
    "state": "active",
    "version": null,
    "license_id": "other-pd",
    "type": "dataset",
    "resources": [
        {
            "resource_group_id": "062a4256-a887-4956-9037-9d13801c728f",
            "cache_last_updated": null,
            "revision_timestamp": "2013-10-10T12:16:47.471028",
            "webstore_last_updated": "2013-10-10T12:16:47.400565",
            "id": "00c1aac6-ffa9-426a-a84a-ec4ba4a04605",
            "size": "264",
            "state": "active",
            "hash": "c3fd65a98e540af9ce84791994bc18d74e4b6647",
            "description": "",
            "format": "CSV",
            "tracking_summary": {
                "total": 0,
                "recent": 0
            },
            "mimetype_inner": null,
            "mimetype": "text/csv",
            "cache_url": null,
            "name": "Uasin Gishu Age Pyramid.csv",
            "created": "2012-09-11T13:31:27.251500",
            "url": "http://africaopendata.org/storage/f/2012-09-11T153412/9ete-q9fq.csv",
            "webstore_url": "active",
            "last_modified": "2013-03-14T10:43:16.982278",
            "position": 0,
            "revision_id": "2441c39b-fc49-4ec0-9139-99ee33dc2430",
            "resource_type": "file.upload",
            "resource_reachable": true
        }
    ],
    "num_resources": 1,
    "tags": [
        {
            "vocabulary_id": null,
            "display_name": "kenya",
            "name": "kenya",
            "revision_timestamp": "2012-09-10T11:59:44.672681",
            "state": "active",
            "id": "3f582e66-8113-4a99-8d18-5647ab436eda"
        },
        {
            "vocabulary_id": null,
            "display_name": "kodi",
            "name": "kodi",
            "revision_timestamp": "2012-09-10T11:59:44.672681",
            "state": "active",
            "id": "8c95d71f-854f-4c7a-8eda-6dfc008df9c1"
        },
        {
            "vocabulary_id": null,
            "display_name": "population",
            "name": "population",
            "revision_timestamp": "2012-09-10T11:59:44.672681",
            "state": "active",
            "id": "c5e39de5-556e-4bcb-883b-5b9ec2481ae9"
        }
    ],
    "tracking_summary": {
        "total": 45,
        "recent": 5
    },
    "groups": [
        {
            "title": "Kenya",
            "description": "Datasets from Kenya",
            "name": "kenya",
            "id": "cdaf12d8-27b2-4cd4-9504-402a45012576"
        }
    ],
    "relationships_as_subject": [],
    "num_tags": 3,
    "name": "kodi-9ete-q9fq",
    "isopen": true,
    "url": "http://www.knbs.or.ke",
    "notes": "Male and female population by age group.",
    "title": "Uasin Gishu Age Pyramid",
    "extras": [
        {
            "value": "KNBS",
            "key": "attribution",
            "__extras": {
                "revision_id": "f6b85703-ba4c-4be8-8b4c-39303fc1c953",
                "package_id": "f1efbe98-ae6e-457e-945c-bb3ef1e61028"
            }
        },
        {
            "value": "Population",
            "key": "category",
            "__extras": {
                "revision_id": "f6b85703-ba4c-4be8-8b4c-39303fc1c953",
                "package_id": "f1efbe98-ae6e-457e-945c-bb3ef1e61028"
            }
        },
        {
            "value": "This dataset has been automatically imported from the Kenya Open Data Portal",
            "key": "comment",
            "__extras": {
                "revision_id": "f6b85703-ba4c-4be8-8b4c-39303fc1c953",
                "package_id": "f1efbe98-ae6e-457e-945c-bb3ef1e61028"
            }
        }
    ],
    "organization": null,
    "revision_id": "f6b85703-ba4c-4be8-8b4c-39303fc1c953"
}