{
    "license_title": "CC0 1.0",
    "maintainer": "Jasper Soetendal",
    "relationships_as_object": [],
    "private": false,
    "maintainer_email": "j.soetendal@braxwell.com",
    "revision_timestamp": "2013-05-16T09:27:24.675354",
    "id": "a3b78ef5-6078-4de3-8fb3-04bb3300d782",
    "metadata_created": "2013-05-16T09:27:24.675354",
    "owner_org": null,
    "metadata_modified": "2013-05-16T09:27:24.675354",
    "author": "CIBG",
    "author_email": "info@bigregister.nl",
    "state": "active",
    "version": "",
    "license_id": "CC0-1.0",
    "type": "dataset",
    "resources": [
        {
            "resource_group_id": "aa99e6ab-bba0-47e9-8eae-3e7e51b8283f",
            "cache_last_updated": null,
            "revision_timestamp": "2013-05-16T09:27:24.675354",
            "webstore_last_updated": null,
            "id": "bbbcbe38-acbd-45be-957c-0a54eee0108e",
            "size": null,
            "source": "None",
            "state": "active",
            "hash": "",
            "description": "API (SOAP/XML)",
            "format": "n/a",
            "tracking_summary": {
                "total": 0,
                "recent": 0
            },
            "mimetype_inner": null,
            "mimetype": null,
            "cache_url": null,
            "name": "http://www.bigregister.nl/zoeken/zoeken_eigen_systeem/",
            "created": "2013-05-16T11:27:24.737314",
            "url": "http://www.bigregister.nl/zoeken/zoeken_eigen_systeem/",
            "webstore_url": null,
            "last_modified": null,
            "position": 0,
            "revision_id": "70e4154d-002b-4159-89ff-e394f4fe614f",
            "resource_type": "file"
        }
    ],
    "num_resources": 1,
    "tags": [
        {
            "vocabulary_id": null,
            "display_name": "BIG",
            "name": "BIG",
            "revision_timestamp": "2013-05-16T09:27:24.675354",
            "state": "active",
            "id": "5b263174-399c-4fda-ba26-486e198a7e09"
        },
        {
            "vocabulary_id": null,
            "display_name": "gezondheidszorg",
            "name": "gezondheidszorg",
            "revision_timestamp": "2013-05-16T09:27:24.675354",
            "state": "active",
            "id": "f822f916-4067-47fa-9075-bafe596485e2"
        },
        {
            "vocabulary_id": null,
            "display_name": "register\n",
            "name": "register\n",
            "revision_timestamp": "2013-05-16T09:27:24.675354",
            "state": "active",
            "id": "df370bc9-5d5f-4359-a725-e1cef6abfea6"
        },
        {
            "vocabulary_id": null,
            "display_name": "zorgverleners",
            "name": "zorgverleners",
            "revision_timestamp": "2013-05-16T09:27:24.675354",
            "state": "active",
            "id": "31a2f812-d14d-4eb3-8dc5-b595a442e8bc"
        }
    ],
    "tracking_summary": {
        "total": 0,
        "recent": 0
    },
    "groups": [
        {
            "title": "Zorg & welzijn",
            "description": "",
            "name": "zorg-welzijn",
            "id": "03f76fe0-7556-4f88-9c23-0b318e1c69ed"
        }
    ],
    "relationships_as_subject": [],
    "num_tags": 4,
    "name": "big-register-zorgverleners",
    "isopen": true,
    "url": null,
    "notes": "Het CIBG, een uitvoeringsorganisatie van het Ministerie van Volksgezondheid, Welzijn en Sport, voert het BIG-register. Het BIG-register is een taak die voortkomt uit de Wet BIG (Wet op de Beroepen in de Individuele Gezondheidszorg). Het BIG-register verleent duidelijkheid over de bevoegdheid van een zorgverlener. Er staan meer dan 400.000 zorgverleners geregistreerd in het BIG-register. Iedereen kan het register raadplegen.\n",
    "title": "BIG register Zorgverleners",
    "extras": [
        {
            "value": "info@bigregister.nl",
            "key": "contact_email",
            "__extras": {
                "package_id": "a3b78ef5-6078-4de3-8fb3-04bb3300d782",
                "revision_id": "70e4154d-002b-4159-89ff-e394f4fe614f"
            }
        },
        {
            "value": "CIBG",
            "key": "contact_name",
            "__extras": {
                "revision_id": "70e4154d-002b-4159-89ff-e394f4fe614f",
                "package_id": "a3b78ef5-6078-4de3-8fb3-04bb3300d782"
            }
        },
        {
            "value": "",
            "key": "publication_date",
            "__extras": {
                "revision_id": "70e4154d-002b-4159-89ff-e394f4fe614f",
                "package_id": "a3b78ef5-6078-4de3-8fb3-04bb3300d782"
            }
        },
        {
            "value": "",
            "key": "time_period_detail_level",
            "__extras": {
                "revision_id": "70e4154d-002b-4159-89ff-e394f4fe614f",
                "package_id": "a3b78ef5-6078-4de3-8fb3-04bb3300d782"
            }
        },
        {
            "value": "",
            "key": "time_period_from",
            "__extras": {
                "package_id": "a3b78ef5-6078-4de3-8fb3-04bb3300d782",
                "revision_id": "70e4154d-002b-4159-89ff-e394f4fe614f"
            }
        },
        {
            "value": "",
            "key": "time_period_to",
            "__extras": {
                "package_id": "a3b78ef5-6078-4de3-8fb3-04bb3300d782",
                "revision_id": "70e4154d-002b-4159-89ff-e394f4fe614f"
            }
        },
        {
            "value": "",
            "key": "update_frequency",
            "__extras": {
                "revision_id": "70e4154d-002b-4159-89ff-e394f4fe614f",
                "package_id": "a3b78ef5-6078-4de3-8fb3-04bb3300d782"
            }
        },
        {
            "value": "http://www.bigregister.nl",
            "key": "website",
            "__extras": {
                "package_id": "a3b78ef5-6078-4de3-8fb3-04bb3300d782",
                "revision_id": "70e4154d-002b-4159-89ff-e394f4fe614f"
            }
        }
    ],
    "license_url": "https://creativecommons.org/publicdomain/zero/1.0/",
    "organization": null,
    "revision_id": "70e4154d-002b-4159-89ff-e394f4fe614f",
    "license_information": {
        "domain_content": true,
        "domain_data": true,
        "domain_software": true,
        "family": "",
        "od_conformance": "approved",
        "osd_conformance": "not reviewed",
        "maintainer": "Creative Commons",
        "status": "active"
    }
}