{
    "license_title": "License Not Specified",
    "maintainer": "",
    "relationships_as_object": [],
    "private": false,
    "maintainer_email": "",
    "revision_timestamp": "2013-10-10T22:01:59.748098",
    "id": "2eed623c-52f6-4894-8ea5-51701ab21226",
    "metadata_created": "2010-08-31T08:21:43.322527",
    "owner_org": "1a24e0c3-013b-481d-b25c-f36c651315d8",
    "metadata_modified": "2013-10-10T22:01:59.748098",
    "author": "Jörg Diederich",
    "author_email": "diederich@l3s.de",
    "state": "active",
    "version": "2010-08-27",
    "license_id": "notspecified",
    "type": "dataset",
    "resources": [
        {
            "mimetype": "application/x-gzip",
            "cache_url": null,
            "mimetype_inner": null,
            "hash": "",
            "description": "Download",
            "format": "application/x-ntriples",
            "url": "http://dblp.l3s.de/dblp.rdf.gz",
            "cache_last_updated": null,
            "tracking_summary": {
                "total": 118,
                "recent": 10
            },
            "revision_timestamp": "2010-08-31T08:21:43.322527",
            "webstore_url": null,
            "resource_group_id": "d98f252d-89e3-42d7-9c53-d948078fbd76",
            "state": "active",
            "last_modified": null,
            "webstore_last_updated": null,
            "position": 0,
            "revision_id": "8698603a-c235-4df8-8c90-f2555e2046ca",
            "size": "777487056",
            "id": "728b9a98-8c7a-463d-81ea-4c3fb8a53fb6",
            "resource_type": null,
            "name": null,
            "resource_reachable": true
        },
        {
            "mimetype": null,
            "cache_url": null,
            "mimetype_inner": null,
            "hash": "",
            "description": "SPARQL endpoint",
            "format": "api/sparql",
            "url": "http://dblp.l3s.de/d2r/sparql",
            "cache_last_updated": null,
            "tracking_summary": {
                "total": 59,
                "recent": 3
            },
            "revision_timestamp": "2010-08-31T08:21:43.322527",
            "webstore_url": null,
            "resource_group_id": "d98f252d-89e3-42d7-9c53-d948078fbd76",
            "state": "active",
            "last_modified": null,
            "webstore_last_updated": null,
            "position": 1,
            "revision_id": "8698603a-c235-4df8-8c90-f2555e2046ca",
            "size": null,
            "id": "5d00a833-6f31-4ec4-902a-c6a2091f6438",
            "resource_type": null,
            "name": null
        },
        {
            "mimetype": null,
            "cache_url": null,
            "mimetype_inner": null,
            "hash": "",
            "description": "Example resource",
            "format": "example/rdf+xml",
            "url": "http://dblp.l3s.de/d2r/resource/authors/Chris_Bizer",
            "cache_last_updated": null,
            "tracking_summary": {
                "total": 33,
                "recent": 3
            },
            "revision_timestamp": "2011-07-20T19:57:11.232621",
            "webstore_url": null,
            "resource_group_id": "d98f252d-89e3-42d7-9c53-d948078fbd76",
            "state": "active",
            "last_modified": null,
            "webstore_last_updated": null,
            "position": 2,
            "revision_id": "89fafbaf-c935-4d10-b090-0774165c1e68",
            "size": null,
            "id": "2702ac94-5130-4b5f-9b88-847fe9cb8597",
            "resource_type": null,
            "name": null
        }
    ],
    "num_resources": 3,
    "tags": [
        {
            "vocabulary_id": null,
            "display_name": "format-dc",
            "name": "format-dc",
            "revision_timestamp": "2010-10-07T10:17:06.037571",
            "state": "active",
            "id": "0b675a54-621f-4fdb-850a-ef5d0b1b1ca3"
        },
        {
            "vocabulary_id": null,
            "display_name": "format-foaf",
            "name": "format-foaf",
            "revision_timestamp": "2010-10-07T10:17:06.037571",
            "state": "active",
            "id": "bd737030-1ba6-4913-baaa-bfa2581618b5"
        },
        {
            "vocabulary_id": null,
            "display_name": "format-rdf",
            "name": "format-rdf",
            "revision_timestamp": "2010-08-31T08:21:43.322527",
            "state": "active",
            "id": "9dd6b48e-299d-427b-95a9-b54708459ab9"
        },
        {
            "vocabulary_id": null,
            "display_name": "format-swrc",
            "name": "format-swrc",
            "revision_timestamp": "2010-10-07T10:17:06.037571",
            "state": "active",
            "id": "4e5912c5-7cfb-4ab8-8d67-ea163c87c205"
        },
        {
            "vocabulary_id": null,
            "display_name": "lod",
            "name": "lod",
            "revision_timestamp": "2010-08-31T08:21:43.322527",
            "state": "active",
            "id": "54a512d9-f003-4b79-badf-c85bfa977a7e"
        },
        {
            "vocabulary_id": null,
            "display_name": "lodcloud.nolinks",
            "name": "lodcloud.nolinks",
            "revision_timestamp": "2011-08-10T12:50:23.048307",
            "state": "active",
            "id": "ce89d5e1-b216-44ba-9603-d13fa7b248c4"
        },
        {
            "vocabulary_id": null,
            "display_name": "no-license-metadata",
            "name": "no-license-metadata",
            "revision_timestamp": "2010-10-07T10:17:06.037571",
            "state": "active",
            "id": "fec2bd03-9eb4-4058-a203-61cd691a383c"
        },
        {
            "vocabulary_id": null,
            "display_name": "no-proprietary-vocab",
            "name": "no-proprietary-vocab",
            "revision_timestamp": "2010-10-07T10:17:06.037571",
            "state": "active",
            "id": "aef04cb8-a7aa-4419-8184-396b0ef6e680"
        },
        {
            "vocabulary_id": null,
            "display_name": "no-provenance-metadata",
            "name": "no-provenance-metadata",
            "revision_timestamp": "2010-10-07T10:17:06.037571",
            "state": "active",
            "id": "585e9fca-2d67-4a07-b9d1-5495de054c7a"
        },
        {
            "vocabulary_id": null,
            "display_name": "no-vocab-mappings",
            "name": "no-vocab-mappings",
            "revision_timestamp": "2010-10-07T10:17:06.037571",
            "state": "active",
            "id": "e51273d8-dc60-4cf2-a68d-3cfd33b2c1fc"
        },
        {
            "vocabulary_id": null,
            "display_name": "publications",
            "name": "publications",
            "revision_timestamp": "2010-10-07T10:17:06.037571",
            "state": "active",
            "id": "c93ebe8f-83a0-498c-8704-1de94db149e9"
        },
        {
            "vocabulary_id": null,
            "display_name": "published-by-third-party",
            "name": "published-by-third-party",
            "revision_timestamp": "2010-10-07T10:17:06.037571",
            "state": "active",
            "id": "61a91c2c-78df-4237-9195-faa353244514"
        }
    ],
    "tracking_summary": {
        "total": 725,
        "recent": 13
    },
    "groups": [],
    "relationships_as_subject": [],
    "num_tags": 12,
    "name": "l3s-dblp",
    "isopen": false,
    "url": "http://dblp.l3s.de/d2r/",
    "notes": "D2R Server publishing the DBLP Bibliography Database, hosted at L3S Research Center",
    "title": "DBLP in RDF (L3S)",
    "extras": [
        {
            "value": "http://dblp.l3s.de/d2r/resource/",
            "key": "namespace",
            "__extras": {
                "package_id": "2eed623c-52f6-4894-8ea5-51701ab21226",
                "revision_id": "89fafbaf-c935-4d10-b090-0774165c1e68"
            }
        },
        {
            "value": "DBLP (L3S)",
            "key": "shortname",
            "__extras": {
                "revision_id": "a2f417fe-5bdb-4ea7-946f-fd6bd1837c5d",
                "package_id": "2eed623c-52f6-4894-8ea5-51701ab21226"
            }
        },
        {
            "value": "57674239",
            "key": "triples",
            "__extras": {
                "revision_id": "8ff67cb2-4b44-40ba-b610-3c9696c51d65",
                "package_id": "2eed623c-52f6-4894-8ea5-51701ab21226"
            }
        }
    ],
    "organization": {
        "description": "This group gathers datasets of relevance to educational applications. it includes data about open educational resources (OER) and items which were created with an explicit educational purpose, as well as otherwise relevant datasets (academic publications, video assets, etc). All datasets included should expose linked data, and provide at least a SPARQL endpoint. For any enquiries, please contact the administrators via data@linkededucation.org.",
        "title": "Linked Education Cloud",
        "created": "2012-10-11T12:20:43.297930",
        "approval_status": "approved",
        "revision_timestamp": "2013-01-03T09:51:09.067990",
        "is_organization": true,
        "state": "active",
        "image_url": "",
        "revision_id": "db4324b3-511f-43a7-ae1b-1940b9a5dc93",
        "type": "organization",
        "id": "1a24e0c3-013b-481d-b25c-f36c651315d8",
        "name": "linked-education"
    },
    "revision_id": "56c9c7ba-ef0d-454c-90ec-8aa81e1b1106"
}